SimLight/3d_field_helper.jl
SimLight/__init__.py
SimLight/_version.py
SimLight/aperture.py
SimLight/calc.py
SimLight/diffraction.py
SimLight/field.py
SimLight/lens.py
SimLight/plottools.py
SimLight/propagation.py
SimLight/units.py
SimLight/unwrap.py
SimLight/utils.py
SimLight/zernike.py
SimLight/zernike_coeff.m
SimLight/zernike_fun.m
SimLight-0.1.0.dist-info/LICENSE
SimLight-0.1.0.dist-info/METADATA
SimLight-0.1.0.dist-info/WHEEL
SimLight-0.1.0.dist-info/top_level.txt
SimLight-0.1.0.dist-info/RECORD
